fluxflow_ui/__init__.py
fluxflow_ui/app.py
fluxflow_ui/app_flask.py
fluxflow_ui/py.typed
fluxflow_ui/components/__init__.py
fluxflow_ui/static/style.css
fluxflow_ui/tabs/__init__.py
fluxflow_ui/tabs/generation.py
fluxflow_ui/tabs/training.py
fluxflow_ui/templates/file_browser.html
fluxflow_ui/templates/index.html
fluxflow_ui/utils/__init__.py
fluxflow_ui/utils/config_manager.py
fluxflow_ui/utils/generation_worker.py
fluxflow_ui/utils/training_runner.py
fluxflow_ui-0.4.0.dist-info/licenses/LICENSE
fluxflow_ui-0.4.0.dist-info/METADATA
fluxflow_ui-0.4.0.dist-info/WHEEL
fluxflow_ui-0.4.0.dist-info/entry_points.txt
fluxflow_ui-0.4.0.dist-info/top_level.txt
fluxflow_ui-0.4.0.dist-info/RECORD
