Metadata-Version: 2.4
Name: fluxflow-ui
Version: 0.4.0
Summary: Web UI for FluxFlow text-to-image generation
Author: Daniele Camisani
License: MIT
Project-URL: Homepage, https://github.com/danny-mio/fluxflow-ui
Project-URL: Repository, https://github.com/danny-mio/fluxflow-ui
Project-URL: Documentation, https://github.com/danny-mio/fluxflow-ui/blob/main/README.md
Project-URL: Issues, https://github.com/danny-mio/fluxflow-ui/issues
Keywords: deep-learning,text-to-image,web-ui,flask,gradio
Classifier: Development Status :: 4 - Beta
Classifier: Intended Audience :: Developers
Classifier: Intended Audience :: Science/Research
Classifier: License :: OSI Approved :: MIT License
Classifier: Programming Language :: Python :: 3
Classifier: Programming Language :: Python :: 3.10
Classifier: Programming Language :: Python :: 3.11
Classifier: Programming Language :: Python :: 3.12
Classifier: Topic :: Scientific/Engineering :: Artificial Intelligence
Classifier: Framework :: Flask
Requires-Python: >=3.10
License-File: LICENSE
Requires-Dist: fluxflow-training<0.5.0,>=0.4.0
Requires-Dist: gradio>=4.0.0
Requires-Dist: flask>=3.0.0
Requires-Dist: flask-cors>=4.0.0
Requires-Dist: pyyaml>=6.0.0
Requires-Dist: torch>=2.0.0
Requires-Dist: transformers>=4.30.0
Requires-Dist: safetensors>=0.3.0
Requires-Dist: diffusers>=0.20.0
Requires-Dist: numpy<2.0,>=1.24.0
Requires-Dist: pillow>=9.0.0
Provides-Extra: dev
Requires-Dist: pytest>=7.4.0; extra == "dev"
Requires-Dist: pytest-cov>=4.1.0; extra == "dev"
Requires-Dist: pytest-timeout>=2.1.0; extra == "dev"
Requires-Dist: pytest-mock>=3.11.0; extra == "dev"
Requires-Dist: black>=23.0.0; extra == "dev"
Requires-Dist: flake8>=6.0.0; extra == "dev"
Requires-Dist: isort>=5.12.0; extra == "dev"
Requires-Dist: mypy>=1.4.0; extra == "dev"
Requires-Dist: ruff>=0.1.0; extra == "dev"
Dynamic: license-file
